README.rst
setup.cfg
setup.py
nhl_scraper/cbssports.py
nhl_scraper/espn.py
nhl_scraper/nhl.py
nhl_scraper.egg-info/PKG-INFO
nhl_scraper.egg-info/SOURCES.txt
nhl_scraper.egg-info/dependency_links.txt
nhl_scraper.egg-info/requires.txt
nhl_scraper.egg-info/top_level.txt
nhl_scraper.egg-info/zip-safe