Metadata-Version: 1.2
Name: nhl-scraper
Version: 0.0.3
Summary: Scrape hockey data from various websites
Home-page: http://github.com/spilchen/nhl_scraper
Author: Matt Spilchen
Author-email: matt.spilchen@gmail.com
License: MIT
Platform: UNKNOWN
Classifier: Development Status :: 3 - Alpha
Classifier: Intended Audience :: Developers
Classifier: License :: OSI Approved :: MIT License
Classifier: Programming Language :: Python :: 3.7
Requires-Python: >=3
